{
  "formatVersion": 1,
  "database": {
    "version": 1,
    "identityHash": "20e974bbb0759c98089064136f02226b",
    "entities": [
      {
        "tableName": "fotos",
        "createSql": "CREATE TABLE IF NOT EXISTS `${TABLE_NAME}` (`id_foto` INTEGER PRIMARY KEY AUTOINCREMENT NOT NULL, `id_ficha` INTEGER NOT NULL, `nombre_foto` TEXT, `fieldbook` INTEGER NOT NULL, `vista` INTEGER NOT NULL, `plano` INTEGER NOT NULL, `fecha` TEXT, `hora` TEXT, `favorita` INTEGER NOT NULL, `ruta` TEXT, `id_visita_foto` INTEGER NOT NULL)",
        "fields": [
          {
            "fieldPath": "id_foto",
            "columnName": "id_foto",
            "affinity": "INTEGER",
            "notNull": true
          },
          {
            "fieldPath": "id_ficha",
            "columnName": "id_ficha",
            "affinity": "INTEGER",
            "notNull": true
          },
          {
            "fieldPath": "nombre_foto",
            "columnName": "nombre_foto",
            "affinity": "TEXT",
            "notNull": false
          },
          {
            "fieldPath": "fieldbook",
            "columnName": "fieldbook",
            "affinity": "INTEGER",
            "notNull": true
          },
          {
            "fieldPath": "vista",
            "columnName": "vista",
            "affinity": "INTEGER",
            "notNull": true
          },
          {
            "fieldPath": "plano",
            "columnName": "plano",
            "affinity": "INTEGER",
            "notNull": true
          },
          {
            "fieldPath": "fecha",
            "columnName": "fecha",
            "affinity": "TEXT",
            "notNull": false
          },
          {
            "fieldPath": "hora",
            "columnName": "hora",
            "affinity": "TEXT",
            "notNull": false
          },
          {
            "fieldPath": "favorita",
            "columnName": "favorita",
            "affinity": "INTEGER",
            "notNull": true
          },
          {
            "fieldPath": "ruta",
            "columnName": "ruta",
            "affinity": "TEXT",
            "notNull": false
          },
          {
            "fieldPath": "id_visita_foto",
            "columnName": "id_visita_foto",
            "affinity": "INTEGER",
            "notNull": true
          }
        ],
        "primaryKey": {
          "columnNames": [
            "id_foto"
          ],
          "autoGenerate": true
        },
        "indices": [],
        "foreignKeys": []
      },
      {
        "tableName": "fichas",
        "createSql": "CREATE TABLE IF NOT EXISTS `${TABLE_NAME}` (`id_ficha` INTEGER PRIMARY KEY AUTOINCREMENT NOT NULL, `anno` INTEGER NOT NULL, `id_agricultor_ficha` INTEGER NOT NULL, `oferta_negocio` TEXT, `id_region_ficha` INTEGER NOT NULL, `id_comuna_ficha` INTEGER NOT NULL, `localidad` TEXT, `has_disponible` REAL NOT NULL, `observaciones` TEXT, `norting` REAL NOT NULL, `easting` REAL NOT NULL, `activa` INTEGER NOT NULL, `subida` INTEGER NOT NULL)",
        "fields": [
          {
            "fieldPath": "id_ficha",
            "columnName": "id_ficha",
            "affinity": "INTEGER",
            "notNull": true
          },
          {
            "fieldPath": "anno",
            "columnName": "anno",
            "affinity": "INTEGER",
            "notNull": true
          },
          {
            "fieldPath": "id_agricultor_ficha",
            "columnName": "id_agricultor_ficha",
            "affinity": "INTEGER",
            "notNull": true
          },
          {
            "fieldPath": "oferta_negocio",
            "columnName": "oferta_negocio",
            "affinity": "TEXT",
            "notNull": false
          },
          {
            "fieldPath": "id_region_ficha",
            "columnName": "id_region_ficha",
            "affinity": "INTEGER",
            "notNull": true
          },
          {
            "fieldPath": "id_comuna_ficha",
            "columnName": "id_comuna_ficha",
            "affinity": "INTEGER",
            "notNull": true
          },
          {
            "fieldPath": "localidad",
            "columnName": "localidad",
            "affinity": "TEXT",
            "notNull": false
          },
          {
            "fieldPath": "has_disponible",
            "columnName": "has_disponible",
            "affinity": "REAL",
            "notNull": true
          },
          {
            "fieldPath": "observaciones",
            "columnName": "observaciones",
            "affinity": "TEXT",
            "notNull": false
          },
          {
            "fieldPath": "norting",
            "columnName": "norting",
            "affinity": "REAL",
            "notNull": true
          },
          {
            "fieldPath": "easting",
            "columnName": "easting",
            "affinity": "REAL",
            "notNull": true
          },
          {
            "fieldPath": "activa",
            "columnName": "activa",
            "affinity": "INTEGER",
            "notNull": true
          },
          {
            "fieldPath": "subida",
            "columnName": "subida",
            "affinity": "INTEGER",
            "notNull": true
          }
        ],
        "primaryKey": {
          "columnNames": [
            "id_ficha"
          ],
          "autoGenerate": true
        },
        "indices": [],
        "foreignKeys": []
      },
      {
        "tableName": "agricultor",
        "createSql": "CREATE TABLE IF NOT EXISTS `${TABLE_NAME}` (`id_agricultor` INTEGER NOT NULL, `rut_agricultor` TEXT NOT NULL, `nombre_agricultor` TEXT, `telefono_agricultor` TEXT, `administrador_agricultor` TEXT, `telefono_admin_agricultor` TEXT, `region_agricultor` INTEGER NOT NULL, `comuna_agricultor` INTEGER NOT NULL, `agricultor_subido` INTEGER NOT NULL, PRIMARY KEY(`id_agricultor`))",
        "fields": [
          {
            "fieldPath": "id_agricultor",
            "columnName": "id_agricultor",
            "affinity": "INTEGER",
            "notNull": true
          },
          {
            "fieldPath": "rut_agricultor",
            "columnName": "rut_agricultor",
            "affinity": "TEXT",
            "notNull": true
          },
          {
            "fieldPath": "nombre_agricultor",
            "columnName": "nombre_agricultor",
            "affinity": "TEXT",
            "notNull": false
          },
          {
            "fieldPath": "telefono_agricultor",
            "columnName": "telefono_agricultor",
            "affinity": "TEXT",
            "notNull": false
          },
          {
            "fieldPath": "administrador_agricultor",
            "columnName": "administrador_agricultor",
            "affinity": "TEXT",
            "notNull": false
          },
          {
            "fieldPath": "telefono_admin_agricultor",
            "columnName": "telefono_admin_agricultor",
            "affinity": "TEXT",
            "notNull": false
          },
          {
            "fieldPath": "region_agricultor",
            "columnName": "region_agricultor",
            "affinity": "INTEGER",
            "notNull": true
          },
          {
            "fieldPath": "comuna_agricultor",
            "columnName": "comuna_agricultor",
            "affinity": "INTEGER",
            "notNull": true
          },
          {
            "fieldPath": "agricultor_subido",
            "columnName": "agricultor_subido",
            "affinity": "INTEGER",
            "notNull": true
          }
        ],
        "primaryKey": {
          "columnNames": [
            "id_agricultor"
          ],
          "autoGenerate": false
        },
        "indices": [],
        "foreignKeys": []
      },
      {
        "tableName": "region",
        "createSql": "CREATE TABLE IF NOT EXISTS `${TABLE_NAME}` (`id_region` INTEGER NOT NULL, `desc_region` TEXT, `id_pais` INTEGER NOT NULL, PRIMARY KEY(`id_region`))",
        "fields": [
          {
            "fieldPath": "id_region",
            "columnName": "id_region",
            "affinity": "INTEGER",
            "notNull": true
          },
          {
            "fieldPath": "desc_region",
            "columnName": "desc_region",
            "affinity": "TEXT",
            "notNull": false
          },
          {
            "fieldPath": "id_pais",
            "columnName": "id_pais",
            "affinity": "INTEGER",
            "notNull": true
          }
        ],
        "primaryKey": {
          "columnNames": [
            "id_region"
          ],
          "autoGenerate": false
        },
        "indices": [],
        "foreignKeys": []
      },
      {
        "tableName": "comuna",
        "createSql": "CREATE TABLE IF NOT EXISTS `${TABLE_NAME}` (`id_comuna` INTEGER NOT NULL, `desc_comuna` TEXT, `id_provincia_comuna` INTEGER NOT NULL, PRIMARY KEY(`id_comuna`))",
        "fields": [
          {
            "fieldPath": "id_comuna",
            "columnName": "id_comuna",
            "affinity": "INTEGER",
            "notNull": true
          },
          {
            "fieldPath": "desc_comuna",
            "columnName": "desc_comuna",
            "affinity": "TEXT",
            "notNull": false
          },
          {
            "fieldPath": "id_provincia_comuna",
            "columnName": "id_provincia_comuna",
            "affinity": "INTEGER",
            "notNull": true
          }
        ],
        "primaryKey": {
          "columnNames": [
            "id_comuna"
          ],
          "autoGenerate": false
        },
        "indices": [],
        "foreignKeys": []
      },
      {
        "tableName": "anexo_contrato",
        "createSql": "CREATE TABLE IF NOT EXISTS `${TABLE_NAME}` (`id_anexo_contrato` INTEGER NOT NULL, `anexo_contrato` TEXT, `id_variedad_anexo` INTEGER NOT NULL, `temporada_anexo` TEXT, `id_especie_anexo` INTEGER NOT NULL, `id_agricultor_anexo` INTEGER NOT NULL, `protero` TEXT, `id_ficha_contrato` INTEGER NOT NULL, PRIMARY KEY(`id_anexo_contrato`))",
        "fields": [
          {
            "fieldPath": "id_anexo_contrato",
            "columnName": "id_anexo_contrato",
            "affinity": "INTEGER",
            "notNull": true
          },
          {
            "fieldPath": "anexo_contrato",
            "columnName": "anexo_contrato",
            "affinity": "TEXT",
            "notNull": false
          },
          {
            "fieldPath": "id_variedad_anexo",
            "columnName": "id_variedad_anexo",
            "affinity": "INTEGER",
            "notNull": true
          },
          {
            "fieldPath": "temporada_anexo",
            "columnName": "temporada_anexo",
            "affinity": "TEXT",
            "notNull": false
          },
          {
            "fieldPath": "id_especie_anexo",
            "columnName": "id_especie_anexo",
            "affinity": "INTEGER",
            "notNull": true
          },
          {
            "fieldPath": "id_agricultor_anexo",
            "columnName": "id_agricultor_anexo",
            "affinity": "INTEGER",
            "notNull": true
          },
          {
            "fieldPath": "protero",
            "columnName": "protero",
            "affinity": "TEXT",
            "notNull": false
          },
          {
            "fieldPath": "id_ficha_contrato",
            "columnName": "id_ficha_contrato",
            "affinity": "INTEGER",
            "notNull": true
          }
        ],
        "primaryKey": {
          "columnNames": [
            "id_anexo_contrato"
          ],
          "autoGenerate": false
        },
        "indices": [],
        "foreignKeys": []
      },
      {
        "tableName": "especie",
        "createSql": "CREATE TABLE IF NOT EXISTS `${TABLE_NAME}` (`id_especie` INTEGER NOT NULL, `desc_especie` TEXT, PRIMARY KEY(`id_especie`))",
        "fields": [
          {
            "fieldPath": "id_especie",
            "columnName": "id_especie",
            "affinity": "INTEGER",
            "notNull": true
          },
          {
            "fieldPath": "desc_especie",
            "columnName": "desc_especie",
            "affinity": "TEXT",
            "notNull": false
          }
        ],
        "primaryKey": {
          "columnNames": [
            "id_especie"
          ],
          "autoGenerate": false
        },
        "indices": [],
        "foreignKeys": []
      },
      {
        "tableName": "variedad",
        "createSql": "CREATE TABLE IF NOT EXISTS `${TABLE_NAME}` (`id_variedad` INTEGER NOT NULL, `id_especie_variedad` INTEGER NOT NULL, `desc_variedad` TEXT, `desc_hibrido_variedad` TEXT, PRIMARY KEY(`id_variedad`))",
        "fields": [
          {
            "fieldPath": "id_variedad",
            "columnName": "id_variedad",
            "affinity": "INTEGER",
            "notNull": true
          },
          {
            "fieldPath": "id_especie_variedad",
            "columnName": "id_especie_variedad",
            "affinity": "INTEGER",
            "notNull": true
          },
          {
            "fieldPath": "desc_variedad",
            "columnName": "desc_variedad",
            "affinity": "TEXT",
            "notNull": false
          },
          {
            "fieldPath": "desc_hibrido_variedad",
            "columnName": "desc_hibrido_variedad",
            "affinity": "TEXT",
            "notNull": false
          }
        ],
        "primaryKey": {
          "columnNames": [
            "id_variedad"
          ],
          "autoGenerate": false
        },
        "indices": [],
        "foreignKeys": []
      },
      {
        "tableName": "temp_visitas",
        "createSql": "CREATE TABLE IF NOT EXISTS `${TABLE_NAME}` (`id_temp_visita` INTEGER PRIMARY KEY AUTOINCREMENT NOT NULL, `id_anexo_temp_visita` INTEGER NOT NULL, `phenological_state_temp_visita` TEXT, `growth_status_temp_visita` TEXT, `weed_state_temp_visita` TEXT, `phytosanitary_state_temp_visita` TEXT, `harvest_temp_visita` TEXT, `overall_status_temp_visita` TEXT, `humidity_floor_temp_visita` TEXT, `observation_temp_visita` TEXT, `recomendation_temp_visita` TEXT, `obs_fito` TEXT, `obs_creci` TEXT, `obs_maleza` TEXT, `obs_cosecha` TEXT, `obs_overall` TEXT, `obs_humedad` TEXT, `action_temp_visita` INTEGER NOT NULL, `etapa_temp_visitas` INTEGER NOT NULL)",
        "fields": [
          {
            "fieldPath": "id_temp_visita",
            "columnName": "id_temp_visita",
            "affinity": "INTEGER",
            "notNull": true
          },
          {
            "fieldPath": "id_anexo_temp_visita",
            "columnName": "id_anexo_temp_visita",
            "affinity": "INTEGER",
            "notNull": true
          },
          {
            "fieldPath": "phenological_state_temp_visita",
            "columnName": "phenological_state_temp_visita",
            "affinity": "TEXT",
            "notNull": false
          },
          {
            "fieldPath": "growth_status_temp_visita",
            "columnName": "growth_status_temp_visita",
            "affinity": "TEXT",
            "notNull": false
          },
          {
            "fieldPath": "weed_state_temp_visita",
            "columnName": "weed_state_temp_visita",
            "affinity": "TEXT",
            "notNull": false
          },
          {
            "fieldPath": "phytosanitary_state_temp_visita",
            "columnName": "phytosanitary_state_temp_visita",
            "affinity": "TEXT",
            "notNull": false
          },
          {
            "fieldPath": "harvest_temp_visita",
            "columnName": "harvest_temp_visita",
            "affinity": "TEXT",
            "notNull": false
          },
          {
            "fieldPath": "overall_status_temp_visita",
            "columnName": "overall_status_temp_visita",
            "affinity": "TEXT",
            "notNull": false
          },
          {
            "fieldPath": "humidity_floor_temp_visita",
            "columnName": "humidity_floor_temp_visita",
            "affinity": "TEXT",
            "notNull": false
          },
          {
            "fieldPath": "observation_temp_visita",
            "columnName": "observation_temp_visita",
            "affinity": "TEXT",
            "notNull": false
          },
          {
            "fieldPath": "recomendation_temp_visita",
            "columnName": "recomendation_temp_visita",
            "affinity": "TEXT",
            "notNull": false
          },
          {
            "fieldPath": "obs_fito",
            "columnName": "obs_fito",
            "affinity": "TEXT",
            "notNull": false
          },
          {
            "fieldPath": "obs_creci",
            "columnName": "obs_creci",
            "affinity": "TEXT",
            "notNull": false
          },
          {
            "fieldPath": "obs_maleza",
            "columnName": "obs_maleza",
            "affinity": "TEXT",
            "notNull": false
          },
          {
            "fieldPath": "obs_cosecha",
            "columnName": "obs_cosecha",
            "affinity": "TEXT",
            "notNull": false
          },
          {
            "fieldPath": "obs_overall",
            "columnName": "obs_overall",
            "affinity": "TEXT",
            "notNull": false
          },
          {
            "fieldPath": "obs_humedad",
            "columnName": "obs_humedad",
            "affinity": "TEXT",
            "notNull": false
          },
          {
            "fieldPath": "action_temp_visita",
            "columnName": "action_temp_visita",
            "affinity": "INTEGER",
            "notNull": true
          },
          {
            "fieldPath": "etapa_temp_visitas",
            "columnName": "etapa_temp_visitas",
            "affinity": "INTEGER",
            "notNull": true
          }
        ],
        "primaryKey": {
          "columnNames": [
            "id_temp_visita"
          ],
          "autoGenerate": true
        },
        "indices": [],
        "foreignKeys": []
      },
      {
        "tableName": "temp_flowering",
        "createSql": "CREATE TABLE IF NOT EXISTS `${TABLE_NAME}` (`id_temp_flowering` INTEGER PRIMARY KEY AUTOINCREMENT NOT NULL, `id_anexo_temp_flowering` INTEGER NOT NULL, `date_notice_sag_temp_flowering` TEXT, `flowering_estimation_temp_flowering` TEXT, `flowering_start_temp_flowering` TEXT, `flowering_end_temp_flowering` TEXT, `fertility_1_temp_flowering` TEXT, `fertility_2_temp_flowering` TEXT, `fungicide_name_temp_flowering` TEXT, `dose_fungicide_temp_flowering` TEXT, `date_funficide_temp_flowering` TEXT, `date_insecticide_temp_flowering` TEXT, `date_beginning_depuration_temp_flowering` TEXT, `date_off_type_temp_flowering` TEXT, `plant_number_checked_temp_flowering` TEXT, `check_temp_flowering` TEXT, `main_characteristic_temp_flowering` TEXT, `date_inspection_temp_flowering` TEXT, `action_temp_flowering` INTEGER NOT NULL)",
        "fields": [
          {
            "fieldPath": "id_temp_flowering",
            "columnName": "id_temp_flowering",
            "affinity": "INTEGER",
            "notNull": true
          },
          {
            "fieldPath": "id_anexo_temp_flowering",
            "columnName": "id_anexo_temp_flowering",
            "affinity": "INTEGER",
            "notNull": true
          },
          {
            "fieldPath": "date_notice_sag_temp_flowering",
            "columnName": "date_notice_sag_temp_flowering",
            "affinity": "TEXT",
            "notNull": false
          },
          {
            "fieldPath": "flowering_estimation_temp_flowering",
            "columnName": "flowering_estimation_temp_flowering",
            "affinity": "TEXT",
            "notNull": false
          },
          {
            "fieldPath": "flowering_start_temp_flowering",
            "columnName": "flowering_start_temp_flowering",
            "affinity": "TEXT",
            "notNull": false
          },
          {
            "fieldPath": "flowering_end_temp_flowering",
            "columnName": "flowering_end_temp_flowering",
            "affinity": "TEXT",
            "notNull": false
          },
          {
            "fieldPath": "fertility_1_temp_flowering",
            "columnName": "fertility_1_temp_flowering",
            "affinity": "TEXT",
            "notNull": false
          },
          {
            "fieldPath": "fertility_2_temp_flowering",
            "columnName": "fertility_2_temp_flowering",
            "affinity": "TEXT",
            "notNull": false
          },
          {
            "fieldPath": "fungicide_name_temp_flowering",
            "columnName": "fungicide_name_temp_flowering",
            "affinity": "TEXT",
            "notNull": false
          },
          {
            "fieldPath": "dose_fungicide_temp_flowering",
            "columnName": "dose_fungicide_temp_flowering",
            "affinity": "TEXT",
            "notNull": false
          },
          {
            "fieldPath": "date_funficide_temp_flowering",
            "columnName": "date_funficide_temp_flowering",
            "affinity": "TEXT",
            "notNull": false
          },
          {
            "fieldPath": "date_insecticide_temp_flowering",
            "columnName": "date_insecticide_temp_flowering",
            "affinity": "TEXT",
            "notNull": false
          },
          {
            "fieldPath": "date_beginning_depuration_temp_flowering",
            "columnName": "date_beginning_depuration_temp_flowering",
            "affinity": "TEXT",
            "notNull": false
          },
          {
            "fieldPath": "date_off_type_temp_flowering",
            "columnName": "date_off_type_temp_flowering",
            "affinity": "TEXT",
            "notNull": false
          },
          {
            "fieldPath": "plant_number_checked_temp_flowering",
            "columnName": "plant_number_checked_temp_flowering",
            "affinity": "TEXT",
            "notNull": false
          },
          {
            "fieldPath": "check_temp_flowering",
            "columnName": "check_temp_flowering",
            "affinity": "TEXT",
            "notNull": false
          },
          {
            "fieldPath": "main_characteristic_temp_flowering",
            "columnName": "main_characteristic_temp_flowering",
            "affinity": "TEXT",
            "notNull": false
          },
          {
            "fieldPath": "date_inspection_temp_flowering",
            "columnName": "date_inspection_temp_flowering",
            "affinity": "TEXT",
            "notNull": false
          },
          {
            "fieldPath": "action_temp_flowering",
            "columnName": "action_temp_flowering",
            "affinity": "INTEGER",
            "notNull": true
          }
        ],
        "primaryKey": {
          "columnNames": [
            "id_temp_flowering"
          ],
          "autoGenerate": true
        },
        "indices": [],
        "foreignKeys": []
      },
      {
        "tableName": "temp_harvest",
        "createSql": "CREATE TABLE IF NOT EXISTS `${TABLE_NAME}` (`id_temp_harvest` INTEGER PRIMARY KEY AUTOINCREMENT NOT NULL, `id_anexo_temp_harvest` INTEGER NOT NULL, `estimated_date_temp_harvest` TEXT, `real_date_temp_harvest` TEXT, `observation_dessicant_temp_harvest` TEXT, `swathing_date_temp_harvest` TEXT, `kg_ha_yield_temp_harvest` TEXT, `observation_yield_temp_harvest` TEXT, `date_harvest_estimation_temp_harvest` TEXT, `beginning_date_temp_harvest` TEXT, `end_date_temp_harvest` TEXT, `owner_machine_temp_harvest` TEXT, `model_machine_temp_harvest` TEXT, `porcent_temp_harvest` REAL NOT NULL, `action_temp_harvest` INTEGER NOT NULL)",
        "fields": [
          {
            "fieldPath": "id_temp_harvest",
            "columnName": "id_temp_harvest",
            "affinity": "INTEGER",
            "notNull": true
          },
          {
            "fieldPath": "id_anexo_temp_harvest",
            "columnName": "id_anexo_temp_harvest",
            "affinity": "INTEGER",
            "notNull": true
          },
          {
            "fieldPath": "estimated_date_temp_harvest",
            "columnName": "estimated_date_temp_harvest",
            "affinity": "TEXT",
            "notNull": false
          },
          {
            "fieldPath": "real_date_temp_harvest",
            "columnName": "real_date_temp_harvest",
            "affinity": "TEXT",
            "notNull": false
          },
          {
            "fieldPath": "observation_dessicant_temp_harvest",
            "columnName": "observation_dessicant_temp_harvest",
            "affinity": "TEXT",
            "notNull": false
          },
          {
            "fieldPath": "swathing_date_temp_harvest",
            "columnName": "swathing_date_temp_harvest",
            "affinity": "TEXT",
            "notNull": false
          },
          {
            "fieldPath": "kg_ha_yield_temp_harvest",
            "columnName": "kg_ha_yield_temp_harvest",
            "affinity": "TEXT",
            "notNull": false
          },
          {
            "fieldPath": "observation_yield_temp_harvest",
            "columnName": "observation_yield_temp_harvest",
            "affinity": "TEXT",
            "notNull": false
          },
          {
            "fieldPath": "date_harvest_estimation_temp_harvest",
            "columnName": "date_harvest_estimation_temp_harvest",
            "affinity": "TEXT",
            "notNull": false
          },
          {
            "fieldPath": "beginning_date_temp_harvest",
            "columnName": "beginning_date_temp_harvest",
            "affinity": "TEXT",
            "notNull": false
          },
          {
            "fieldPath": "end_date_temp_harvest",
            "columnName": "end_date_temp_harvest",
            "affinity": "TEXT",
            "notNull": false
          },
          {
            "fieldPath": "owner_machine_temp_harvest",
            "columnName": "owner_machine_temp_harvest",
            "affinity": "TEXT",
            "notNull": false
          },
          {
            "fieldPath": "model_machine_temp_harvest",
            "columnName": "model_machine_temp_harvest",
            "affinity": "TEXT",
            "notNull": false
          },
          {
            "fieldPath": "porcent_temp_harvest",
            "columnName": "porcent_temp_harvest",
            "affinity": "REAL",
            "notNull": true
          },
          {
            "fieldPath": "action_temp_harvest",
            "columnName": "action_temp_harvest",
            "affinity": "INTEGER",
            "notNull": true
          }
        ],
        "primaryKey": {
          "columnNames": [
            "id_temp_harvest"
          ],
          "autoGenerate": true
        },
        "indices": [],
        "foreignKeys": []
      },
      {
        "tableName": "visitas",
        "createSql": "CREATE TABLE IF NOT EXISTS `${TABLE_NAME}` (`id_visita` INTEGER PRIMARY KEY AUTOINCREMENT NOT NULL, `id_anexo_visita` INTEGER NOT NULL, `phenological_state_visita` TEXT, `growth_status_visita` TEXT, `weed_state_visita` TEXT, `phytosanitary_state_visita` TEXT, `harvest_visita` TEXT, `overall_status_visita` TEXT, `humidity_floor_visita` TEXT, `observation_visita` TEXT, `recomendation_visita` TEXT, `estado_server_visitas` INTEGER NOT NULL, `estado_visita` INTEGER NOT NULL, `etapa_visitas` INTEGER NOT NULL, `fecha_visita` TEXT, `hora_visita` TEXT, `temporada` INTEGER NOT NULL, `obs_fito` TEXT, `obs_creci` TEXT, `obs_maleza` TEXT, `obs_cosecha` TEXT, `obs_overall` TEXT, `obs_humedad` TEXT)",
        "fields": [
          {
            "fieldPath": "id_visita",
            "columnName": "id_visita",
            "affinity": "INTEGER",
            "notNull": true
          },
          {
            "fieldPath": "id_anexo_visita",
            "columnName": "id_anexo_visita",
            "affinity": "INTEGER",
            "notNull": true
          },
          {
            "fieldPath": "phenological_state_visita",
            "columnName": "phenological_state_visita",
            "affinity": "TEXT",
            "notNull": false
          },
          {
            "fieldPath": "growth_status_visita",
            "columnName": "growth_status_visita",
            "affinity": "TEXT",
            "notNull": false
          },
          {
            "fieldPath": "weed_state_visita",
            "columnName": "weed_state_visita",
            "affinity": "TEXT",
            "notNull": false
          },
          {
            "fieldPath": "phytosanitary_state_visita",
            "columnName": "phytosanitary_state_visita",
            "affinity": "TEXT",
            "notNull": false
          },
          {
            "fieldPath": "harvest_visita",
            "columnName": "harvest_visita",
            "affinity": "TEXT",
            "notNull": false
          },
          {
            "fieldPath": "overall_status_visita",
            "columnName": "overall_status_visita",
            "affinity": "TEXT",
            "notNull": false
          },
          {
            "fieldPath": "humidity_floor_visita",
            "columnName": "humidity_floor_visita",
            "affinity": "TEXT",
            "notNull": false
          },
          {
            "fieldPath": "observation_visita",
            "columnName": "observation_visita",
            "affinity": "TEXT",
            "notNull": false
          },
          {
            "fieldPath": "recomendation_visita",
            "columnName": "recomendation_visita",
            "affinity": "TEXT",
            "notNull": false
          },
          {
            "fieldPath": "estado_server_visitas",
            "columnName": "estado_server_visitas",
            "affinity": "INTEGER",
            "notNull": true
          },
          {
            "fieldPath": "estado_visita",
            "columnName": "estado_visita",
            "affinity": "INTEGER",
            "notNull": true
          },
          {
            "fieldPath": "etapa_visitas",
            "columnName": "etapa_visitas",
            "affinity": "INTEGER",
            "notNull": true
          },
          {
            "fieldPath": "fecha_visita",
            "columnName": "fecha_visita",
            "affinity": "TEXT",
            "notNull": false
          },
          {
            "fieldPath": "hora_visita",
            "columnName": "hora_visita",
            "affinity": "TEXT",
            "notNull": false
          },
          {
            "fieldPath": "temporada",
            "columnName": "temporada",
            "affinity": "INTEGER",
            "notNull": true
          },
          {
            "fieldPath": "obs_fito",
            "columnName": "obs_fito",
            "affinity": "TEXT",
            "notNull": false
          },
          {
            "fieldPath": "obs_creci",
            "columnName": "obs_creci",
            "affinity": "TEXT",
            "notNull": false
          },
          {
            "fieldPath": "obs_maleza",
            "columnName": "obs_maleza",
            "affinity": "TEXT",
            "notNull": false
          },
          {
            "fieldPath": "obs_cosecha",
            "columnName": "obs_cosecha",
            "affinity": "TEXT",
            "notNull": false
          },
          {
            "fieldPath": "obs_overall",
            "columnName": "obs_overall",
            "affinity": "TEXT",
            "notNull": false
          },
          {
            "fieldPath": "obs_humedad",
            "columnName": "obs_humedad",
            "affinity": "TEXT",
            "notNull": false
          }
        ],
        "primaryKey": {
          "columnNames": [
            "id_visita"
          ],
          "autoGenerate": true
        },
        "indices": [],
        "foreignKeys": []
      },
      {
        "tableName": "sowing",
        "createSql": "CREATE TABLE IF NOT EXISTS `${TABLE_NAME}` (`id_sowing` INTEGER PRIMARY KEY AUTOINCREMENT NOT NULL, `id_anexo_sowing` INTEGER NOT NULL, `id_visita_sowing` INTEGER NOT NULL, `estado_server_sowing` INTEGER NOT NULL, `sag_planting_sowing` TEXT, `delivered_sowing` TEXT, `type_of_mixture_applied_sowing` TEXT, `amount_applied_sowing` TEXT, `meters_isoliation_sowing` INTEGER NOT NULL, `south_sowing` TEXT, `north_sowing` TEXT, `east_sowing` TEXT, `west_sowing` TEXT, `female_lines_sowing` TEXT, `female_sowing_lot_sowing` TEXT, `real_sowing_female_sowing` REAL NOT NULL, `female_sowing_date_start_sowing` TEXT, `female_sowing_date_end_sowing` TEXT, `sowing_seed_meter_sowing` REAL NOT NULL, `row_distance_sowing` REAL NOT NULL, `dose_1_sowing` TEXT, `date_1_sowing` TEXT, `dose_2_sowing` TEXT, `date_2_sowing` TEXT, `name_1_herb_sowing` TEXT, `date_1_herb_sowing` TEXT, `name_2_herb_sowing` TEXT, `date_2_herb_sowing` TEXT, `name_3_herb_sowing` TEXT, `date_3_herb_sowing` TEXT, `date_pre_emergence_sowing` TEXT, `dose_pre_emergence_sowing` TEXT, `water_pre_emergence_sowing` REAL NOT NULL, `plant_m_sowing` REAL NOT NULL, `population_plants_ha_sowing` REAL NOT NULL, `basta_spray_1_sowing` TEXT, `basta_spray_2_sowing` TEXT, `basta_spray_3_sowing` TEXT, `basta_spray_4_sowing` TEXT, `basta_splat_4_ha_sowing` TEXT, `date_nombre_largo_sowing` TEXT, `product_nombre_largo_sowing` TEXT, `dose_nombre_largo_sowing` TEXT, `foliar_sowing` TEXT, `dose_foliar_sowing` TEXT, `date_foliar_sowing` TEXT)",
        "fields": [
          {
            "fieldPath": "id_sowing",
            "columnName": "id_sowing",
            "affinity": "INTEGER",
            "notNull": true
          },
          {
            "fieldPath": "id_anexo_sowing",
            "columnName": "id_anexo_sowing",
            "affinity": "INTEGER",
            "notNull": true
          },
          {
            "fieldPath": "id_visita_sowing",
            "columnName": "id_visita_sowing",
            "affinity": "INTEGER",
            "notNull": true
          },
          {
            "fieldPath": "estado_server_sowing",
            "columnName": "estado_server_sowing",
            "affinity": "INTEGER",
            "notNull": true
          },
          {
            "fieldPath": "sag_planting_sowing",
            "columnName": "sag_planting_sowing",
            "affinity": "TEXT",
            "notNull": false
          },
          {
            "fieldPath": "delivered_sowing",
            "columnName": "delivered_sowing",
            "affinity": "TEXT",
            "notNull": false
          },
          {
            "fieldPath": "type_of_mixture_applied_sowing",
            "columnName": "type_of_mixture_applied_sowing",
            "affinity": "TEXT",
            "notNull": false
          },
          {
            "fieldPath": "amount_applied_sowing",
            "columnName": "amount_applied_sowing",
            "affinity": "TEXT",
            "notNull": false
          },
          {
            "fieldPath": "meters_isoliation_sowing",
            "columnName": "meters_isoliation_sowing",
            "affinity": "INTEGER",
            "notNull": true
          },
          {
            "fieldPath": "south_sowing",
            "columnName": "south_sowing",
            "affinity": "TEXT",
            "notNull": false
          },
          {
            "fieldPath": "north_sowing",
            "columnName": "north_sowing",
            "affinity": "TEXT",
            "notNull": false
          },
          {
            "fieldPath": "east_sowing",
            "columnName": "east_sowing",
            "affinity": "TEXT",
            "notNull": false
          },
          {
            "fieldPath": "west_sowing",
            "columnName": "west_sowing",
            "affinity": "TEXT",
            "notNull": false
          },
          {
            "fieldPath": "female_lines_sowing",
            "columnName": "female_lines_sowing",
            "affinity": "TEXT",
            "notNull": false
          },
          {
            "fieldPath": "female_sowing_lot_sowing",
            "columnName": "female_sowing_lot_sowing",
            "affinity": "TEXT",
            "notNull": false
          },
          {
            "fieldPath": "real_sowing_female_sowing",
            "columnName": "real_sowing_female_sowing",
            "affinity": "REAL",
            "notNull": true
          },
          {
            "fieldPath": "female_sowing_date_start_sowing",
            "columnName": "female_sowing_date_start_sowing",
            "affinity": "TEXT",
            "notNull": false
          },
          {
            "fieldPath": "female_sowing_date_end_sowing",
            "columnName": "female_sowing_date_end_sowing",
            "affinity": "TEXT",
            "notNull": false
          },
          {
            "fieldPath": "sowing_seed_meter_sowing",
            "columnName": "sowing_seed_meter_sowing",
            "affinity": "REAL",
            "notNull": true
          },
          {
            "fieldPath": "row_distance_sowing",
            "columnName": "row_distance_sowing",
            "affinity": "REAL",
            "notNull": true
          },
          {
            "fieldPath": "dose_1_sowing",
            "columnName": "dose_1_sowing",
            "affinity": "TEXT",
            "notNull": false
          },
          {
            "fieldPath": "date_1_sowing",
            "columnName": "date_1_sowing",
            "affinity": "TEXT",
            "notNull": false
          },
          {
            "fieldPath": "dose_2_sowing",
            "columnName": "dose_2_sowing",
            "affinity": "TEXT",
            "notNull": false
          },
          {
            "fieldPath": "date_2_sowing",
            "columnName": "date_2_sowing",
            "affinity": "TEXT",
            "notNull": false
          },
          {
            "fieldPath": "name_1_herb_sowing",
            "columnName": "name_1_herb_sowing",
            "affinity": "TEXT",
            "notNull": false
          },
          {
            "fieldPath": "date_1_herb_sowing",
            "columnName": "date_1_herb_sowing",
            "affinity": "TEXT",
            "notNull": false
          },
          {
            "fieldPath": "name_2_herb_sowing",
            "columnName": "name_2_herb_sowing",
            "affinity": "TEXT",
            "notNull": false
          },
          {
            "fieldPath": "date_2_herb_sowing",
            "columnName": "date_2_herb_sowing",
            "affinity": "TEXT",
            "notNull": false
          },
          {
            "fieldPath": "name_3_herb_sowing",
            "columnName": "name_3_herb_sowing",
            "affinity": "TEXT",
            "notNull": false
          },
          {
            "fieldPath": "date_3_herb_sowing",
            "columnName": "date_3_herb_sowing",
            "affinity": "TEXT",
            "notNull": false
          },
          {
            "fieldPath": "date_pre_emergence_sowing",
            "columnName": "date_pre_emergence_sowing",
            "affinity": "TEXT",
            "notNull": false
          },
          {
            "fieldPath": "dose_pre_emergence_sowing",
            "columnName": "dose_pre_emergence_sowing",
            "affinity": "TEXT",
            "notNull": false
          },
          {
            "fieldPath": "water_pre_emergence_sowing",
            "columnName": "water_pre_emergence_sowing",
            "affinity": "REAL",
            "notNull": true
          },
          {
            "fieldPath": "plant_m_sowing",
            "columnName": "plant_m_sowing",
            "affinity": "REAL",
            "notNull": true
          },
          {
            "fieldPath": "population_plants_ha_sowing",
            "columnName": "population_plants_ha_sowing",
            "affinity": "REAL",
            "notNull": true
          },
          {
            "fieldPath": "basta_spray_1_sowing",
            "columnName": "basta_spray_1_sowing",
            "affinity": "TEXT",
            "notNull": false
          },
          {
            "fieldPath": "basta_spray_2_sowing",
            "columnName": "basta_spray_2_sowing",
            "affinity": "TEXT",
            "notNull": false
          },
          {
            "fieldPath": "basta_spray_3_sowing",
            "columnName": "basta_spray_3_sowing",
            "affinity": "TEXT",
            "notNull": false
          },
          {
            "fieldPath": "basta_spray_4_sowing",
            "columnName": "basta_spray_4_sowing",
            "affinity": "TEXT",
            "notNull": false
          },
          {
            "fieldPath": "basta_splat_4_ha_sowing",
            "columnName": "basta_splat_4_ha_sowing",
            "affinity": "TEXT",
            "notNull": false
          },
          {
            "fieldPath": "date_nombre_largo_sowing",
            "columnName": "date_nombre_largo_sowing",
            "affinity": "TEXT",
            "notNull": false
          },
          {
            "fieldPath": "product_nombre_largo_sowing",
            "columnName": "product_nombre_largo_sowing",
            "affinity": "TEXT",
            "notNull": false
          },
          {
            "fieldPath": "dose_nombre_largo_sowing",
            "columnName": "dose_nombre_largo_sowing",
            "affinity": "TEXT",
            "notNull": false
          },
          {
            "fieldPath": "foliar_sowing",
            "columnName": "foliar_sowing",
            "affinity": "TEXT",
            "notNull": false
          },
          {
            "fieldPath": "dose_foliar_sowing",
            "columnName": "dose_foliar_sowing",
            "affinity": "TEXT",
            "notNull": false
          },
          {
            "fieldPath": "date_foliar_sowing",
            "columnName": "date_foliar_sowing",
            "affinity": "TEXT",
            "notNull": false
          }
        ],
        "primaryKey": {
          "columnNames": [
            "id_sowing"
          ],
          "autoGenerate": true
        },
        "indices": [],
        "foreignKeys": []
      },
      {
        "tableName": "flowering",
        "createSql": "CREATE TABLE IF NOT EXISTS `${TABLE_NAME}` (`id_flowering` INTEGER PRIMARY KEY AUTOINCREMENT NOT NULL, `id_anexo_flowering` INTEGER NOT NULL, `id_visita_flowering` INTEGER NOT NULL, `estado_server_flowering` INTEGER NOT NULL, `date_notice_sag_flowering` TEXT, `flowering_estimation_flowering` TEXT, `flowering_start_flowering` TEXT, `flowering_end_flowering` TEXT, `fertility_1_flowering` TEXT, `fertility_2_flowering` TEXT, `fungicide_name_flowering` TEXT, `dose_fungicide_flowering` TEXT, `date_funficide_flowering` TEXT, `date_insecticide_flowering` TEXT, `date_beginning_depuration_flowering` TEXT, `date_off_type_flowering` TEXT, `plant_number_checked_flowering` TEXT, `check_flowering` TEXT, `main_characteristic_flowering` TEXT, `date_inspection_flowering` TEXT)",
        "fields": [
          {
            "fieldPath": "id_flowering",
            "columnName": "id_flowering",
            "affinity": "INTEGER",
            "notNull": true
          },
          {
            "fieldPath": "id_anexo_flowering",
            "columnName": "id_anexo_flowering",
            "affinity": "INTEGER",
            "notNull": true
          },
          {
            "fieldPath": "id_visita_flowering",
            "columnName": "id_visita_flowering",
            "affinity": "INTEGER",
            "notNull": true
          },
          {
            "fieldPath": "estado_server_flowering",
            "columnName": "estado_server_flowering",
            "affinity": "INTEGER",
            "notNull": true
          },
          {
            "fieldPath": "date_notice_sag_flowering",
            "columnName": "date_notice_sag_flowering",
            "affinity": "TEXT",
            "notNull": false
          },
          {
            "fieldPath": "flowering_estimation_flowering",
            "columnName": "flowering_estimation_flowering",
            "affinity": "TEXT",
            "notNull": false
          },
          {
            "fieldPath": "flowering_start_flowering",
            "columnName": "flowering_start_flowering",
            "affinity": "TEXT",
            "notNull": false
          },
          {
            "fieldPath": "flowering_end_flowering",
            "columnName": "flowering_end_flowering",
            "affinity": "TEXT",
            "notNull": false
          },
          {
            "fieldPath": "fertility_1_flowering",
            "columnName": "fertility_1_flowering",
            "affinity": "TEXT",
            "notNull": false
          },
          {
            "fieldPath": "fertility_2_flowering",
            "columnName": "fertility_2_flowering",
            "affinity": "TEXT",
            "notNull": false
          },
          {
            "fieldPath": "fungicide_name_flowering",
            "columnName": "fungicide_name_flowering",
            "affinity": "TEXT",
            "notNull": false
          },
          {
            "fieldPath": "dose_fungicide_flowering",
            "columnName": "dose_fungicide_flowering",
            "affinity": "TEXT",
            "notNull": false
          },
          {
            "fieldPath": "date_funficide_flowering",
            "columnName": "date_funficide_flowering",
            "affinity": "TEXT",
            "notNull": false
          },
          {
            "fieldPath": "date_insecticide_flowering",
            "columnName": "date_insecticide_flowering",
            "affinity": "TEXT",
            "notNull": false
          },
          {
            "fieldPath": "date_beginning_depuration_flowering",
            "columnName": "date_beginning_depuration_flowering",
            "affinity": "TEXT",
            "notNull": false
          },
          {
            "fieldPath": "date_off_type_flowering",
            "columnName": "date_off_type_flowering",
            "affinity": "TEXT",
            "notNull": false
          },
          {
            "fieldPath": "plant_number_checked_flowering",
            "columnName": "plant_number_checked_flowering",
            "affinity": "TEXT",
            "notNull": false
          },
          {
            "fieldPath": "check_flowering",
            "columnName": "check_flowering",
            "affinity": "TEXT",
            "notNull": false
          },
          {
            "fieldPath": "main_characteristic_flowering",
            "columnName": "main_characteristic_flowering",
            "affinity": "TEXT",
            "notNull": false
          },
          {
            "fieldPath": "date_inspection_flowering",
            "columnName": "date_inspection_flowering",
            "affinity": "TEXT",
            "notNull": false
          }
        ],
        "primaryKey": {
          "columnNames": [
            "id_flowering"
          ],
          "autoGenerate": true
        },
        "indices": [],
        "foreignKeys": []
      },
      {
        "tableName": "harvest",
        "createSql": "CREATE TABLE IF NOT EXISTS `${TABLE_NAME}` (`id_temp_harvest` INTEGER PRIMARY KEY AUTOINCREMENT NOT NULL, `id_anexo_temp_harvest` INTEGER NOT NULL, `id_visita_harvest` INTEGER NOT NULL, `estado_server_harvest` INTEGER NOT NULL, `estimated_date_temp_harvest` TEXT, `real_date_temp_harvest` TEXT, `observation_dessicant_temp_harvest` TEXT, `swathing_date_temp_harvest` TEXT, `kg_ha_yield_temp_harvest` TEXT, `observation_yield_temp_harvest` TEXT, `date_harvest_estimation_temp_harvest` TEXT, `beginning_date_temp_harvest` TEXT, `end_date_temp_harvest` TEXT, `owner_machine_temp_harvest` TEXT, `model_machine_temp_harvest` TEXT, `porcent_temp_harvest` REAL NOT NULL)",
        "fields": [
          {
            "fieldPath": "id_temp_harvest",
            "columnName": "id_temp_harvest",
            "affinity": "INTEGER",
            "notNull": true
          },
          {
            "fieldPath": "id_anexo_temp_harvest",
            "columnName": "id_anexo_temp_harvest",
            "affinity": "INTEGER",
            "notNull": true
          },
          {
            "fieldPath": "id_visita_harvest",
            "columnName": "id_visita_harvest",
            "affinity": "INTEGER",
            "notNull": true
          },
          {
            "fieldPath": "estado_server_harvest",
            "columnName": "estado_server_harvest",
            "affinity": "INTEGER",
            "notNull": true
          },
          {
            "fieldPath": "estimated_date_temp_harvest",
            "columnName": "estimated_date_temp_harvest",
            "affinity": "TEXT",
            "notNull": false
          },
          {
            "fieldPath": "real_date_temp_harvest",
            "columnName": "real_date_temp_harvest",
            "affinity": "TEXT",
            "notNull": false
          },
          {
            "fieldPath": "observation_dessicant_temp_harvest",
            "columnName": "observation_dessicant_temp_harvest",
            "affinity": "TEXT",
            "notNull": false
          },
          {
            "fieldPath": "swathing_date_temp_harvest",
            "columnName": "swathing_date_temp_harvest",
            "affinity": "TEXT",
            "notNull": false
          },
          {
            "fieldPath": "kg_ha_yield_temp_harvest",
            "columnName": "kg_ha_yield_temp_harvest",
            "affinity": "TEXT",
            "notNull": false
          },
          {
            "fieldPath": "observation_yield_temp_harvest",
            "columnName": "observation_yield_temp_harvest",
            "affinity": "TEXT",
            "notNull": false
          },
          {
            "fieldPath": "date_harvest_estimation_temp_harvest",
            "columnName": "date_harvest_estimation_temp_harvest",
            "affinity": "TEXT",
            "notNull": false
          },
          {
            "fieldPath": "beginning_date_temp_harvest",
            "columnName": "beginning_date_temp_harvest",
            "affinity": "TEXT",
            "notNull": false
          },
          {
            "fieldPath": "end_date_temp_harvest",
            "columnName": "end_date_temp_harvest",
            "affinity": "TEXT",
            "notNull": false
          },
          {
            "fieldPath": "owner_machine_temp_harvest",
            "columnName": "owner_machine_temp_harvest",
            "affinity": "TEXT",
            "notNull": false
          },
          {
            "fieldPath": "model_machine_temp_harvest",
            "columnName": "model_machine_temp_harvest",
            "affinity": "TEXT",
            "notNull": false
          },
          {
            "fieldPath": "porcent_temp_harvest",
            "columnName": "porcent_temp_harvest",
            "affinity": "REAL",
            "notNull": true
          }
        ],
        "primaryKey": {
          "columnNames": [
            "id_temp_harvest"
          ],
          "autoGenerate": true
        },
        "indices": [],
        "foreignKeys": []
      },
      {
        "tableName": "crop_rotation",
        "createSql": "CREATE TABLE IF NOT EXISTS `${TABLE_NAME}` (`id_crop_rotation` INTEGER NOT NULL, `temporada_crop_rotation` INTEGER NOT NULL, `cultivo_crop_rotation` TEXT, `id_ficha_crop_rotation` INTEGER NOT NULL, `id_anexo_crop_rotation` INTEGER NOT NULL, PRIMARY KEY(`id_crop_rotation`))",
        "fields": [
          {
            "fieldPath": "id_crop_rotation",
            "columnName": "id_crop_rotation",
            "affinity": "INTEGER",
            "notNull": true
          },
          {
            "fieldPath": "temporada_crop_rotation",
            "columnName": "temporada_crop_rotation",
            "affinity": "INTEGER",
            "notNull": true
          },
          {
            "fieldPath": "cultivo_crop_rotation",
            "columnName": "cultivo_crop_rotation",
            "affinity": "TEXT",
            "notNull": false
          },
          {
            "fieldPath": "id_ficha_crop_rotation",
            "columnName": "id_ficha_crop_rotation",
            "affinity": "INTEGER",
            "notNull": true
          },
          {
            "fieldPath": "id_anexo_crop_rotation",
            "columnName": "id_anexo_crop_rotation",
            "affinity": "INTEGER",
            "notNull": true
          }
        ],
        "primaryKey": {
          "columnNames": [
            "id_crop_rotation"
          ],
          "autoGenerate": false
        },
        "indices": [],
        "foreignKeys": []
      },
      {
        "tableName": "pro_cli_mat",
        "createSql": "CREATE TABLE IF NOT EXISTS `${TABLE_NAME}` (`id_prop_mat_cli` INTEGER NOT NULL, `id_cli` INTEGER NOT NULL, `id_materiales` INTEGER NOT NULL, `id_prop` INTEGER NOT NULL, `id_etapa` INTEGER NOT NULL, `id_tempo` INTEGER NOT NULL, `nombre_es` TEXT, `nombre_en` TEXT, `nombre_elemento` TEXT, `aplica` TEXT, `orden` INTEGER NOT NULL, `tipo_cambio` TEXT, `es_lista` TEXT, PRIMARY KEY(`id_prop_mat_cli`))",
        "fields": [
          {
            "fieldPath": "id_prop_mat_cli",
            "columnName": "id_prop_mat_cli",
            "affinity": "INTEGER",
            "notNull": true
          },
          {
            "fieldPath": "id_cli",
            "columnName": "id_cli",
            "affinity": "INTEGER",
            "notNull": true
          },
          {
            "fieldPath": "id_materiales",
            "columnName": "id_materiales",
            "affinity": "INTEGER",
            "notNull": true
          },
          {
            "fieldPath": "id_prop",
            "columnName": "id_prop",
            "affinity": "INTEGER",
            "notNull": true
          },
          {
            "fieldPath": "id_etapa",
            "columnName": "id_etapa",
            "affinity": "INTEGER",
            "notNull": true
          },
          {
            "fieldPath": "id_tempo",
            "columnName": "id_tempo",
            "affinity": "INTEGER",
            "notNull": true
          },
          {
            "fieldPath": "nombre_es",
            "columnName": "nombre_es",
            "affinity": "TEXT",
            "notNull": false
          },
          {
            "fieldPath": "nombre_en",
            "columnName": "nombre_en",
            "affinity": "TEXT",
            "notNull": false
          },
          {
            "fieldPath": "nombre_elemento",
            "columnName": "nombre_elemento",
            "affinity": "TEXT",
            "notNull": false
          },
          {
            "fieldPath": "aplica",
            "columnName": "aplica",
            "affinity": "TEXT",
            "notNull": false
          },
          {
            "fieldPath": "orden",
            "columnName": "orden",
            "affinity": "INTEGER",
            "notNull": true
          },
          {
            "fieldPath": "tipo_cambio",
            "columnName": "tipo_cambio",
            "affinity": "TEXT",
            "notNull": false
          },
          {
            "fieldPath": "es_lista",
            "columnName": "es_lista",
            "affinity": "TEXT",
            "notNull": false
          }
        ],
        "primaryKey": {
          "columnNames": [
            "id_prop_mat_cli"
          ],
          "autoGenerate": false
        },
        "indices": [],
        "foreignKeys": []
      },
      {
        "tableName": "temporada",
        "createSql": "CREATE TABLE IF NOT EXISTS `${TABLE_NAME}` (`id_tempo_tempo` INTEGER NOT NULL, `nombre_tempo` TEXT, `desde_tempo` TEXT, `hasta_tempo` TEXT, PRIMARY KEY(`id_tempo_tempo`))",
        "fields": [
          {
            "fieldPath": "id_tempo_tempo",
            "columnName": "id_tempo_tempo",
            "affinity": "INTEGER",
            "notNull": true
          },
          {
            "fieldPath": "nombre_tempo",
            "columnName": "nombre_tempo",
            "affinity": "TEXT",
            "notNull": false
          },
          {
            "fieldPath": "desde_tempo",
            "columnName": "desde_tempo",
            "affinity": "TEXT",
            "notNull": false
          },
          {
            "fieldPath": "hasta_tempo",
            "columnName": "hasta_tempo",
            "affinity": "TEXT",
            "notNull": false
          }
        ],
        "primaryKey": {
          "columnNames": [
            "id_tempo_tempo"
          ],
          "autoGenerate": false
        },
        "indices": [],
        "foreignKeys": []
      },
      {
        "tableName": "detalle_visita_prop",
        "createSql": "CREATE TABLE IF NOT EXISTS `${TABLE_NAME}` (`id_det_vis_prop_detalle` INTEGER PRIMARY KEY AUTOINCREMENT NOT NULL, `id_visita_detalle` INTEGER NOT NULL, `id_prop_mat_cli_detalle` INTEGER NOT NULL, `valor_detalle` TEXT, `estado_detalle` INTEGER NOT NULL)",
        "fields": [
          {
            "fieldPath": "id_det_vis_prop_detalle",
            "columnName": "id_det_vis_prop_detalle",
            "affinity": "INTEGER",
            "notNull": true
          },
          {
            "fieldPath": "id_visita_detalle",
            "columnName": "id_visita_detalle",
            "affinity": "INTEGER",
            "notNull": true
          },
          {
            "fieldPath": "id_prop_mat_cli_detalle",
            "columnName": "id_prop_mat_cli_detalle",
            "affinity": "INTEGER",
            "notNull": true
          },
          {
            "fieldPath": "valor_detalle",
            "columnName": "valor_detalle",
            "affinity": "TEXT",
            "notNull": false
          },
          {
            "fieldPath": "estado_detalle",
            "columnName": "estado_detalle",
            "affinity": "INTEGER",
            "notNull": true
          }
        ],
        "primaryKey": {
          "columnNames": [
            "id_det_vis_prop_detalle"
          ],
          "autoGenerate": true
        },
        "indices": [],
        "foreignKeys": []
      },
      {
        "tableName": "provincia",
        "createSql": "CREATE TABLE IF NOT EXISTS `${TABLE_NAME}` (`id_provincia` INTEGER NOT NULL, `nombre_provincia` TEXT, `id_region_provincia` INTEGER NOT NULL, PRIMARY KEY(`id_provincia`))",
        "fields": [
          {
            "fieldPath": "id_provincia",
            "columnName": "id_provincia",
            "affinity": "INTEGER",
            "notNull": true
          },
          {
            "fieldPath": "nombre_provincia",
            "columnName": "nombre_provincia",
            "affinity": "TEXT",
            "notNull": false
          },
          {
            "fieldPath": "id_region_provincia",
            "columnName": "id_region_provincia",
            "affinity": "INTEGER",
            "notNull": true
          }
        ],
        "primaryKey": {
          "columnNames": [
            "id_provincia"
          ],
          "autoGenerate": false
        },
        "indices": [],
        "foreignKeys": []
      }
    ],
    "setupQueries": [
      "CREATE TABLE IF NOT EXISTS room_master_table (id INTEGER PRIMARY KEY,identity_hash TEXT)",
      "INSERT OR REPLACE INTO room_master_table (id,identity_hash) VALUES(42, \"20e974bbb0759c98089064136f02226b\")"
    ]
  }
}